verysimplemodulexxp/__init__.py
verysimplemodulexxp/add.py
verysimplemodulexxp-0.0.2.dist-info/METADATA
verysimplemodulexxp-0.0.2.dist-info/WHEEL
verysimplemodulexxp-0.0.2.dist-info/top_level.txt
verysimplemodulexxp-0.0.2.dist-info/RECORD
